dft_python_api/__init__.py
dft_python_api/calculator/__init__.py
dft_python_api/calculator/dft_code_calculator.py
dft_python_api/master/__init__.py
dft_python_api/master/master_io.py
dft_python_api/tasks/__init__.py
dft_python_api/tasks/castep_debug_task.py
dft_python_api/tasks/castep_task.py
dft_python_api/tasks/fortran_example_task.py
dft_python_api/tasks/generic_task.py
dft_python_api/tasks/task.py
dft_python_api/tasks/worker_environment.py
dft_python_api/utils/__init__.py
dft_python_api/utils/controlflags.py
dft_python_api/utils/results.py
dft_python_api/utils/units.py
dft_python_api/worker/__init__.py
dft_python_api/worker/worker.py
dft_python_api/worker/worker_io.py
dft_python_api-0.0.2.dist-info/LICENSE
dft_python_api-0.0.2.dist-info/METADATA
dft_python_api-0.0.2.dist-info/WHEEL
dft_python_api-0.0.2.dist-info/top_level.txt
dft_python_api-0.0.2.dist-info/RECORD
