Metadata-Version: 2.1
Name: dft-python-api
Version: 0.0.2
Summary: Python DFT code APIe
Home-page: https://bitbucket.org/byornski/dft-python-api
Author: Peter Byrne
Author-email: peter.byrne+dftpythonapi@york.ac.uk
License: UNKNOWN
Platform: UNKNOWN
Classifier: Programming Language :: Python :: 3
Classifier: License :: OSI Approved :: MIT License
Classifier: Operating System :: OS Independent
Requires-Python: >=3.6
License-File: LICENSE
Requires-Dist: ase
Requires-Dist: pint
Requires-Dist: psutil
Requires-Dist: mpi4py
